Spruce_types-0.1.1-py2.7-nspkg.pth
spruce/types/_annotated.py
spruce/types/_checking.py
spruce/types/__init__.py
spruce/types/_misc.py
spruce/types/_converters/_core.py
spruce/types/_converters/_re.py
spruce/types/_converters/_string.py
spruce/types/_converters/__init__.py
spruce/types/_converters/_num.py
spruce/types/_converters/_misc.py
Spruce_types-0.1.1.dist-info/METADATA
Spruce_types-0.1.1.dist-info/entry_points.txt
Spruce_types-0.1.1.dist-info/RECORD
Spruce_types-0.1.1.dist-info/top_level.txt
Spruce_types-0.1.1.dist-info/namespace_packages.txt
Spruce_types-0.1.1.dist-info/WHEEL
Spruce_types-0.1.1.dist-info/metadata.json
Spruce_types-0.1.1.dist-info/DESCRIPTION.rst
