Metadata-Version: 2.0
Name: Spruce-types
Version: 0.1.1
Summary: Data types
Home-page: UNKNOWN
Author: Ivan D Vasin
Author-email: nisavid@gmail.com
License: GNU LESSER GENERAL PUBLIC LICENSE
Requires-Dist: spruce-exc
Requires-Dist: spruce-lang
